{
  "$schema": "https://json-schema.org/draft/2020-12/schema",
  "$id": "#/components/schemas/ProfileNoGroupMembershipCondition",
  "title": "ProfileNoGroupMembershipCondition",
  "type": "object",
  "properties": {
    "type": {
      "type": "string",
      "enum": [
        "profile-group-membership"
      ]
    },
    "is_member": {
      "type": "boolean",
      "enum": [
        false
      ]
    },
    "group_ids": {
      "type": "array",
      "items": {
        "type": "string"
      }
    }
  },
  "required": [
    "type",
    "is_member",
    "group_ids"
  ]
}